{
    "coupans": [
      {
        "id": "1",
        "store": "amazon",
        "long_offer": "Extra 25% OFF on Running shoes, apparel, and accessories",
        "title": "Flat 15% OFF",
        "description": "This promotional offer is valid on Running shoes, apparel, and accessories",
        "code": "RUNALL25",
        "categories": "Fashion,Footwear,Sports and Outdoor,Sportswear,Sports Gear",
        "offer": "Percentage-Off",
        "offer_value": "25%",
        "status": "new",
        "start_date": "2024-06-20",
        "end_date": "2024-08-25",
        "banner_img": "http://localhost:3000/images/product2.jpg",
        "brand_logo": "http://localhost:3000/assets/amazon.jpg",
        "no_of_offers": "15",
        "cashback": "Upto 20.2% Cashback"
      },
      {
        "id": "2",
        "store": "myntra",
        "long_offer": "Mattress starting at just $319",
        "title": "Flat 5% OFF",
        "description": "Starts @ just $319",
        "code": "RUNALL25",
        "categories": "Home and Living,Furniture and Decor",
        "offer": "Percentage-Off",
        "offer_value": "20%",
        "status": "new",
        "start_date": "2024-06-20",
        "end_date": "2024-08-25",
        "banner_img": "http://localhost:3000/img/img1.png",
        "brand_logo": "http://localhost:3000/assets/myntralogo.jpg",
        "no_of_offers": "5",
        "cashback": "Upto 20.2% Cashback"
      },
      {
        "id": "3",
        "store": "myntra",
        "long_offer": "Mattress starting at just $319",
        "title": "Flat 52% OFF",
        "description": "Starts @ just $319",
        "code": "RUNALL25",
        "categories": "Home and Living,Furniture and Decor",
        "offer": "Percentage-Off",
        "offer_value": "20%",
        "status": "new",
        "start_date": "2024-06-20",
        "end_date": "2024-08-25",
        "banner_img": "http://localhost:3000/assets/myntralogo.jpg",
        "brand_logo": "http://localhost:3000/assets/myntralogo.jpg",
        "no_of_offers": "20",
        "cashback": "Upto 20.2% Cashback"
      },
      {
        "id": "4",
        "store": "amazon",
        "long_offer": "Extra 25% OFF on Running shoes, apparel, and accessories",
        "title": "Flat 15% OFF",
        "description": "This promotional offer is valid on Running shoes, apparel, and accessories",
        "code": "RUNALL25",
        "categories": "Fashion,Footwear,Sports and Outdoor,Sportswear,Sports Gear",
        "offer": "Percentage-Off",
        "offer_value": "25%",
        "status": "new",
        "start_date": "2024-06-20",
        "end_date": "2024-08-25",
        "banner_img": "http://localhost:3000/images/product2.jpg",
        "brand_logo": "http://localhost:3000/images/amazon-logo-small.jpg",
        "no_of_offers": "27",
        "cashback": "Upto 20.2% Cashback"
      },
      {
        "id": "5",
        "store": "amazon",
        "long_offer": "Extra 25% OFF on Running shoes, apparel, and accessories",
        "title": "Flat 15% OFF",
        "description": "This promotional offer is valid on Running shoes, apparel, and accessories",
        "code": "RUNALL25",
        "categories": "Beauty",
        "offer": "Percentage-Off",
        "offer_value": "25%",
        "status": "new",
        "start_date": "2024-06-20",
        "end_date": "2024-08-25",
        "banner_img": "http://localhost:3000/img/makeup.webp",
        "brand_logo": "",
        "no_of_offers": "30",
        "cashback": "Upto 20.2% Cashback"
      },
      {
        "id": "6",
        "store": "makemy trip",
        "long_offer": "Extra 25% OFF on Running shoes, apparel, and accessories",
        "title": "Flat 15% OFF",
        "description": "This promotional offer is valid on Running shoes, apparel, and accessories",
        "code": "RUNALL25",
        "categories": "Travel",
        "offer": "Percentage-Off",
        "offer_value": "25%",
        "status": "new",
        "start_date": "2024-06-20",
        "end_date": "2024-08-25",
        "banner_img": "http://localhost:3000/img/travel.jpg",
        "brand_logo": "http://localhost:3000/img/logo3.png",
        "no_of_offers": "25",
        "cashback": "Upto 20.2% Cashback"
      },
      {
        "id": "7",
        "store": "alltricks",
        "long_offer": "Extra 25% OFF on Running shoes, apparel, and accessories",
        "title": "Flat 15% OFF",
        "description": "This promotional offer is valid on Running shoes, apparel, and accessories",
        "code": "RUNALL25",
        "categories": "Mobiles",
        "offer": "Percentage-Off",
        "offer_value": "25%",
        "status": "new",
        "start_date": "2024-06-20",
        "end_date": "2024-08-25",
        "brand_logo": "http://localhost:3000/img/logo4.png",
        "banner_img": "http://localhost:3000/img/mobile1.jpeg",
        "no_of_offers": "25",
        "cashback": "Upto 20.2% Cashback"
      },
      {
        "id": "8",
        "store": "alltricks",
        "long_offer": "Extra 25% OFF on Running shoes, apparel, and accessories",
        "title": "Flat 15% OFF",
        "description": "This promotional offer is valid on Running shoes, apparel, and accessories",
        "code": "RUNALL25",
        "categories": "Mobiles",
        "offer": "Percentage-Off",
        "offer_value": "5%",
        "status": "new",
        "start_date": "2024-06-20",
        "end_date": "2024-08-25",
        "brand_logo": "http://localhost:3000/img/logo5.png",
        "banner_img": "http://localhost:3000/img/mobile2.webp",
        "no_of_offers": "25",
        "cashback": "Upto 20.2% Cashback"
      },
      {
        "id": "8",
        "store": "alltricks",
        "long_offer": "Extra 25% OFF on Running shoes, apparel, and accessories",
        "title": "Flat 15% OFF",
        "description": "This promotional offer is valid on Running shoes, apparel, and accessories",
        "code": "RUNALL25",
        "categories": "Mobiles",
        "offer": "Percentage-Off",
        "offer_value": "5%",
        "status": "new",
        "start_date": "2024-06-20",
        "end_date": "2024-08-25",
        "banner_img": "",
        "brand_logo": "http://localhost:3000/img/logo6.jpg",
        "no_of_offers": "25",
        "cashback": "Upto 20.2% Cashback"
      },
      {
        "id": "8",
        "store": "alltricks",
        "long_offer": "Extra 25% OFF on Running shoes, apparel, and accessories",
        "title": "Flat 15% OFF",
        "description": "This promotional offer is valid on Running shoes, apparel, and accessories",
        "code": "RUNALL25",
        "categories": "Mobiles",
        "offer": "Percentage-Off",
        "offer_value": "5%",
        "status": "new",
        "start_date": "2024-06-20",
        "end_date": "2024-08-25",
        "banner_img": "",
        "brand_logo": "http://localhost:3000/img/logo7.jpg",
        "no_of_offers": "25",
        "cashback": "Upto 20.2% Cashback"
      },
      {
        "id": "9",
        "store": "alltricks.de",
        "long_offer": "Extra 25% OFF on Running shoes, apparel, and accessories",
        "title": "Flat 15% OFF",
        "description": "This promotional offer is valid on Running shoes, apparel, and accessories",
        "code": "RUNALL25",
        "categories": "Mobiles",
        "offer": "Percentage-Off",
        "offer_value": "5%",
        "status": "new",
        "start_date": "2024-06-20",
        "end_date": "2024-08-25",
        "banner_img": "",
        "brand_logo": "http://localhost:3000/img/logo8.jpg",
        "no_of_offers": "25",
        "cashback": "Upto 20.2% Cashback"
      },
      {
        "id": "10",
        "store": "alltricks.de",
        "long_offer": "Extra 25% OFF on Running shoes, apparel, and accessories",
        "title": "Flat 15% OFF",
        "description": "This promotional offer is valid on Running shoes, apparel, and accessories",
        "code": "RUNALL25",
        "categories": "Mobiles",
        "offer": "Percentage-Off",
        "offer_value": "5%",
        "status": "new",
        "start_date": "2024-06-20",
        "end_date": "2024-08-25",
        "banner_img": "",
        "brand_logo": "http://localhost:3000/img/logo9.jpg",
        "no_of_offers": "25",
        "cashback": "Upto 20.2% Cashback"
      }
    ]
  }